filebrowser/models.py
filebrowser/signals.py
filebrowser/urls.py
filebrowser/widgets.py
filebrowser/__init__.py
filebrowser/settings.py
filebrowser/sites.py
filebrowser/actions.py
filebrowser/views.py
filebrowser/base.py
filebrowser/storage.py
filebrowser/fields.py
filebrowser/functions.py
filebrowser/decorators.py
filebrowser/forms.py
filebrowser/templatetags/__init__.py
filebrowser/templatetags/fb_versions.py
filebrowser/templatetags/fb_csrf.py
filebrowser/templatetags/fb_pagination.py
filebrowser/templatetags/fb_tags.py
filebrowser/management/__init__.py
filebrowser/management/commands/fb_version_generate.py
filebrowser/management/commands/__init__.py
filebrowser/management/commands/fb_version_remove.py
filebrowser/tests/__init__.py
filebrowser/tests/settings.py
filebrowser/tests/sites.py
filebrowser/tests/base.py
filebrowser/tests/versions.py
filebrowser/tests/forms.py
filebrowser/static/filebrowser/css/filebrowser.css
filebrowser/static/filebrowser/js/FB_CKEditor.js
filebrowser/static/filebrowser/js/TinyMCEAdmin.js
filebrowser/static/filebrowser/js/AddFileBrowser.js
filebrowser/static/filebrowser/js/FB_TinyMCE.js
filebrowser/static/filebrowser/js/FB_FileBrowseField.js
filebrowser/static/filebrowser/js/fileuploader.js
filebrowser/static/filebrowser/img/filebrowser_type_folder.gif
filebrowser/static/filebrowser/img/filebrowser_icon_select_disabled.gif
filebrowser/static/filebrowser/img/icon-pulldown-actions-hover.png
filebrowser/static/filebrowser/img/filebrowser_icon_delete.gif
filebrowser/static/filebrowser/img/icon-showversions.png
filebrowser/static/filebrowser/img/filebrowser_icon_select.gif
filebrowser/static/filebrowser/img/filebrowser_type_code.gif
filebrowser/static/filebrowser/img/icon-searchbox.png
filebrowser/static/filebrowser/img/icon-pulldown-versions-hover.png
filebrowser/static/filebrowser/img/icon-pulldown-versions-active.png
filebrowser/static/filebrowser/img/icon-fb-preview.png
django_filebrowser_no_grappelli_nph-3.4.9.dist-info/metadata.json
django_filebrowser_no_grappelli_nph-3.4.9.dist-info/RECORD
django_filebrowser_no_grappelli_nph-3.4.9.dist-info/METADATA
django_filebrowser_no_grappelli_nph-3.4.9.dist-info/DESCRIPTION.rst
django_filebrowser_no_grappelli_nph-3.4.9.dist-info/top_level.txt
django_filebrowser_no_grappelli_nph-3.4.9.dist-info/WHEEL
