Metadata-Version: 2.0
Name: django-filebrowser-no-grappelli-nph
Version: 3.4.9
Summary: Media-Management
Home-page: UNKNOWN
Author: Nephila
Author-email: info@nephila.it
License: UNKNOWN
Platform: UNKNOWN
Classifier: Development Status :: 5 - Production/Stable
Classifier: Environment :: Web Environment
Classifier: Framework :: Django
Classifier: Intended Audience :: Developers
Classifier: License :: OSI Approved :: BSD License
Classifier: Operating System :: OS Independent
Classifier: Programming Language :: Python
